firegorest/__init__.py
firegorest/doctools.py
firegorest/types.py
firegorest-0.1.0.dist-info/WHEEL
firegorest-0.1.0.dist-info/METADATA
firegorest-0.1.0.dist-info/RECORD
