Metadata-Version: 2.1
Name: firegorest
Version: 0.1.0
Summary: Some utilties to work with Google Firestore API.
Home-page: https://github.com/sunshine-tech/FireGoRest.git
License: Apache-2.0
Keywords: google,cloud,firestore,functions
Author: Nguyễn Hồng Quân
Author-email: ng.hong.quan@gmail.com
Maintainer: Nguyễn Hồng Quân
Maintainer-email: ng.hong.quan@gmail.com
Requires-Python: >=3.7,<4.0
Classifier: Environment :: Web Environment
Classifier: Intended Audience :: Developers
Classifier: License :: OSI Approved :: Apache Software License
Classifier: Programming Language :: Python :: 3
Classifier: Programming Language :: Python :: 3 :: Only
Classifier: Programming Language :: Python :: 3.7
Classifier: Programming Language :: Python :: 3.8
Classifier: Topic :: Internet
Classifier: Topic :: Utilities
Requires-Dist: importlib_metadata (>=1.4.0,<2.0.0)
Requires-Dist: iso8601 (>=0.1.12,<0.2.0)
Project-URL: Repository, https://github.com/sunshine-tech/FireGoRest.git
